{
  "Respiratory System": [
    "runny nose",
    "sore throat",
    "cough",
    "mild fever",
    "sneezing",
    "shortness of breath",
    "chest tightness",
    "wheezing",
    "coughing",
    "high fever",
    "chills",
    "cough with phlegm",
    "difficulty breathing",
    "fatigue",
    "persistent cough",
    "mucus production",
    "chest discomfort",
    "chronic cough",
    "frequent respiratory infections"
  ],
  "Digestive System": [
    "diarrhea",
    "nausea",
    "vomiting",
    "abdominal cramps",
    "fever",
    "burning stomach pain",
    "bloating",
    "loss of appetite",
    "weight loss",
    "abdominal pain",
    "constipation",
    "gas",
    "infrequent bowel movements",
    "hard stools",
    "discomfort",
    "straining",
    "stomach pain",
    "indigestion",
    "heartburn",
    "regurgitation",
    "chest pain",
    "difficulty swallowing",
    "dry cough",
    "fatigue",
    "swelling in legs",
    "jaundice",
    "upper abdominal pain",
    "rapid pulse",
    "sudden upper right abdomen pain"
  ],
  "Urinary System": [
    "burning sensation during urination",
    "frequent urination",
    "cloudy urine",
    "pelvic pain",
    "strong-smelling urine",
    "intense back or side pain",
    "nausea",
    "blood in urine",
    "painful urination",
    "chronic bladder pressure",
    "bladder pain",
    "pelvic discomfort",
    "urgency",
    "burning urination",
    "fever",
    "chills",
    "back pain"
  ],
  "Oncology": [
    "lump in the breast",
    "nipple discharge",
    "change in breast shape",
    "swelling in part of the breast",
    "skin irritation",
    "chronic cough",
    "chest pain",
    "weight loss",
    "shortness of breath",
    "coughing up blood",
    "frequent infections",
    "fatigue",
    "bleeding easily",
    "fever",
    "frequent urination",
    "weak urine stream",
    "erectile dysfunction",
    "painful ejaculation",
    "pelvic discomfort",
    "changing mole",
    "skin lesion",
    "itching",
    "bleeding from lesion",
    "new skin growth"
  ],
  "Circulatory System": [
    "headaches",
    "shortness of breath",
    "nosebleeds",
    "dizziness",
    "chest pain",
    "fatigue",
    "numbness in limbs",
    "weak pulse",
    "swelling in legs",
    "rapid heartbeat",
    "persistent coughing",
    "leg pain when walking",
    "numbness",
    "cold feet",
    "slow healing wounds",
    "weak pulse in legs",
    "sudden severe headache",
    "blurred vision",
    "nausea",
    "loss of consciousness",
    "stiff neck"
  ],
  "Immune System": [
    "joint pain",
    "swelling",
    "stiffness",
    "fatigue",
    "loss of joint function",
    "skin rash",
    "fever",
    "organ damage",
    "red patches",
    "dry skin",
    "itching",
    "cracked skin",
    "thickened nails",
    "numbness",
    "muscle weakness",
    "vision loss",
    "coordination issues",
    "frequent urination",
    "extreme thirst",
    "blurred vision",
    "weight loss",
    "diarrhea",
    "bloating",
    "rash",
    "weight gain",
    "cold sensitivity",
    "constipation",
    "depression",
    "anxiety",
    "irritability",
    "heat sensitivity",
    "bulging eyes",
    "back pain",
    "reduced flexibility",
    "inflammation",
    "dry mouth",
    "dry eyes"
  ],
  "Cardiovascular System": [
    "headache",
    "dizziness",
    "nosebleeds",
    "blurred vision",
    "chest pain",
    "shortness of breath",
    "fatigue",
    "heart attack",
    "irregular heartbeat",
    "swollen legs",
    "rapid heartbeat",
    "persistent cough",
    "fluttering chest",
    "racing heartbeat",
    "slow heartbeat",
    "numbness",
    "leg pain",
    "high blood pressure",
    "stroke",
    "leg cramps",
    "weak pulse",
    "cold legs",
    "shiny skin",
    "breathlessness",
    "chest pressure",
    "sweating",
    "nausea",
    "fever",
    "chills",
    "muscle aches",
    "sharp chest pain",
    "dry cough"
  ],
  "Nervous System": [
    "seizures",
    "confusion",
    "loss of consciousness",
    "staring spells",
    "temporary paralysis",
    "tremor",
    "slowed movement",
    "muscle stiffness",
    "impaired posture",
    "speech changes",
    "vision problems",
    "muscle weakness",
    "tingling",
    "balance issues",
    "fatigue",
    "memory loss",
    "difficulty thinking",
    "disorientation",
    "behavior changes",
    "intense headache",
    "nausea",
    "sensitivity to light",
    "blurred vision",
    "aura",
    "numbness on one side",
    "difficulty speaking",
    "loss of balance",
    "severe headache",
    "facial droop",
    "inability to close eye",
    "tearing",
    "loss of taste",
    "facial pain",
    "sharp pain",
    "burning sensation",
    "numbness",
    "sensitivity to touch",
    "fever",
    "headache",
    "stiff neck",
    "trouble swallowing",
    "muscle cramps",
    "respiratory issues"
  ],
  "Integumentary System": [
    "pimples",
    "blackheads",
    "whiteheads",
    "oily skin",
    "scarring",
    "itching",
    "red patches",
    "dry skin",
    "blisters",
    "cracking",
    "silvery scales",
    "cracked skin",
    "rash",
    "redness",
    "swelling",
    "scaling",
    "new growths",
    "changing moles",
    "bleeding",
    "non-healing sores",
    "scaly patches"
  ],
  "Skeletal System": [
    "bone fractures",
    "loss of height",
    "back pain",
    "stooped posture",
    "brittle bones",
    "joint pain",
    "stiffness",
    "swelling",
    "reduced motion",
    "grating sensation",
    "delayed growth",
    "bowed legs",
    "muscle weakness",
    "bone pain",
    "soft bones",
    "joint stiffness",
    "bent bones",
    "hearing loss",
    "increased head size",
    "severe pain",
    "bruising",
    "deformity",
    "inability to move limb"
  ],
  "Visual System": [
    "redness",
    "itchy eyes",
    "watery discharge",
    "gritty feeling",
    "crusting eyelids",
    "cloudy vision",
    "difficulty seeing at night",
    "halos around lights",
    "fading colors",
    "double vision",
    "vision loss",
    "eye pain",
    "halo vision",
    "headache",
    "nausea",
    "blurred vision",
    "loss of central vision",
    "difficulty recognizing faces",
    "straight lines appear wavy",
    "dark spots",
    "burning sensation",
    "itchiness",
    "eye fatigue",
    "red eyelids",
    "itching",
    "flaking",
    "crusting",
    "burning",
    "sudden flashes",
    "floaters",
    "shadow over vision",
    "difficulty distinguishing colors",
    "trouble with red-green shades",
    "visual confusion",
    "learning challenges",
    "eye strain",
    "poor depth perception",
    "squinting",
    "eye misalignment",
    "blurry vision",
    "light sensitivity"
  ],
  "Pediatrics": [
    "itchy rash",
    "fever",
    "tiredness",
    "loss of appetite",
    "headache",
    "sore throat",
    "rash on hands and feet",
    "mouth sores",
    "barking cough",
    "stridor",
    "hoarseness",
    "difficulty breathing",
    "wheezing",
    "coughing",
    "rapid breathing",
    "runny nose",
    "ear pain",
    "irritability",
    "trouble hearing",
    "fluid drainage",
    "severe coughing fits",
    "vomiting after cough",
    "fatigue",
    "low-grade fever",
    "bluish skin",
    "swollen cheeks",
    "jaw pain",
    "muscle aches",
    "rash",
    "high fever",
    "cough",
    "red eyes",
    "red rash",
    "swollen glands",
    "flushed face"
  ],
  "Endocrine System": [
    "frequent urination",
    "increased thirst",
    "unexplained weight loss",
    "fatigue",
    "blurred vision",
    "hunger",
    "rapid heartbeat",
    "weight loss",
    "nervousness",
    "tremors",
    "heat intolerance",
    "weight gain",
    "cold sensitivity",
    "dry skin",
    "depression",
    "fatty hump between shoulders",
    "purple stretch marks",
    "high blood pressure",
    "mood swings",
    "low blood pressure",
    "darkened skin",
    "salt craving",
    "irregular periods",
    "acne",
    "excess hair growth",
    "infertility",
    "abnormal growth",
    "delayed puberty",
    "headache",
    "vision problems",
    "excessive sweating",
    "bulging eyes",
    "anxiety",
    "irregular heartbeat",
    "neck swelling",
    "tight throat feeling",
    "coughing",
    "hoarseness",
    "trouble swallowing"
  ],
  "Musculoskeletal System": [
    "bone fragility",
    "back pain",
    "loss of height",
    "stooped posture",
    "easy fractures",
    "joint pain",
    "stiffness",
    "swelling",
    "fatigue",
    "fever",
    "loss of flexibility",
    "grating sensation",
    "bone spurs",
    "pain at joint",
    "warmth",
    "reduced mobility",
    "tenderness",
    "widespread pain",
    "sleep problems",
    "memory issues",
    "mood disturbances"
  ]
}
